feincms3_forms/__init__.py
feincms3_forms/admin.py
feincms3_forms/models.py
feincms3_forms/renderer.py
feincms3_forms/reporting.py
feincms3_forms/validation.py
feincms3_forms/locale/de/LC_MESSAGES/django.mo
feincms3_forms/locale/de/LC_MESSAGES/django.po
feincms3_forms-0.6.0.dist-info/METADATA
feincms3_forms-0.6.0.dist-info/WHEEL
feincms3_forms-0.6.0.dist-info/licenses/LICENSE
feincms3_forms-0.6.0.dist-info/RECORD
